{
  "data": [
    {
      "date": "2026-04-28",
      "ticker": "TSLA",
      "volatility": "0.467503264821165",
      "expiry": "2026-04-29",
      "dte": 1,
      "implied_move": "6.31135352193256",
      "implied_move_perc": "0.01677035000779231"
    },
    {
      "date": "2026-04-28",
      "ticker": "TSLA",
      "volatility": "0.474557195163129",
      "expiry": "2026-05-01",
      "dte": 3,
      "implied_move": "11.02877342471667",
      "implied_move_perc": "0.02930767317889334"
    },
    {
      "date": "2026-04-28",
      "ticker": "TSLA",
      "volatility": "0.4023434444364765",
      "expiry": "2026-05-04",
      "dte": 6,
      "implied_move": "13.21089343693239",
      "implied_move_perc": "0.0351064014410785"
    },
    {
      "date": "2026-04-28",
      "ticker": "TSLA",
      "volatility": "0.4151779552047035",
      "expiry": "2026-05-06",
      "dte": 8,
      "implied_move": "15.73127322595506",
      "implied_move_perc": "0.04180401542758236"
    },
    {
      "date": "2026-04-28",
      "ticker": "TSLA",
      "volatility": "0.4270466324827365",
      "expiry": "2026-05-08",
      "dte": 10,
      "implied_move": "18.08379490394425",
      "implied_move_perc": "0.0480517481637462"
    },
    {
      "date": "2026-04-28",
      "ticker": "TSLA",
      "volatility": "0.4005749196248205",
      "expiry": "2026-05-11",
      "dte": 13,
      "implied_move": "19.27624626621908",
      "implied_move_perc": "0.0512202961848836"
    },
    {
      "date": "2026-04-28",
      "ticker": "TSLA",
      "volatility": "0.404833012994946",
      "expiry": "2026-05-13",
      "dte": 15,
      "implied_move": "20.92177491119979",
      "implied_move_perc": "0.0555927483424558"
    },
    {
      "date": "2026-04-28",
      "ticker": "TSLA",
      "volatility": "0.4159771536508975",
      "expiry": "2026-05-15",
      "dte": 17,
      "implied_move": "22.95486278839125",
      "implied_move_perc": "0.0609950119264263"
    },
    {
      "date": "2026-04-28",
      "ticker": "TSLA",
      "volatility": "0.412091699457198",
      "expiry": "2026-05-22",
      "dte": 24,
      "implied_move": "26.92379661380243",
      "implied_move_perc": "0.071546834947567"
    },
    {
      "date": "2026-04-28",
      "ticker": "TSLA",
      "volatility": "0.400044746096314",
      "expiry": "2026-05-29",
      "dte": 31,
      "implied_move": "29.69874974073693",
      "implied_move_perc": "0.0789209477522313"
    },
    {
      "date": "2026-04-28",
      "ticker": "TSLA",
      "volatility": "0.405853695076687",
      "expiry": "2026-06-05",
      "dte": 38,
      "implied_move": "33.35059617284049",
      "implied_move_perc": "0.0886182605432335"
    },
    {
      "date": "2026-04-28",
      "ticker": "TSLA",
      "volatility": "0.4104276163109995",
      "expiry": "2026-06-18",
      "dte": 51,
      "implied_move": "39.05752651261945",
      "implied_move_perc": "0.1037825819495075"
    },
    {
      "date": "2026-04-28",
      "ticker": "TSLA",
      "volatility": "0.4153470979351525",
      "expiry": "2026-07-17",
      "dte": 80,
      "implied_move": "49.4690672480792",
      "implied_move_perc": "0.1314582501189289"
    },
    {
      "date": "2026-04-28",
      "ticker": "TSLA",
      "volatility": "0.4374097595050235",
      "expiry": "2026-08-21",
      "dte": 115,
      "implied_move": "62.8574998454883",
      "implied_move_perc": "0.1670364410774207"
    },
    {
      "date": "2026-04-28",
      "ticker": "TSLA",
      "volatility": "0.4414230123117125",
      "expiry": "2026-09-18",
      "dte": 143,
      "implied_move": "70.1703119952464",
      "implied_move_perc": "0.1864693825524384"
    },
    {
      "date": "2026-04-28",
      "ticker": "TSLA",
      "volatility": "0.445482827298003",
      "expiry": "2026-10-16",
      "dte": 171,
      "implied_move": "77.382902477347",
      "implied_move_perc": "0.2056359966882287"
    },
    {
      "date": "2026-04-28",
      "ticker": "TSLA",
      "volatility": "0.45690319281482",
      "expiry": "2026-11-20",
      "dte": 206,
      "implied_move": "87.0258476438438",
      "implied_move_perc": "0.231242620087803"
    },
    {
      "date": "2026-04-28",
      "ticker": "TSLA",
      "volatility": "0.458300353263557",
      "expiry": "2026-12-18",
      "dte": 234,
      "implied_move": "92.9665138829024",
      "implied_move_perc": "0.2470476181290441"
    },
    {
      "date": "2026-04-28",
      "ticker": "TSLA",
      "volatility": "0.457102085067519",
      "expiry": "2027-01-15",
      "dte": 262,
      "implied_move": "98.7273948005972",
      "implied_move_perc": "0.2623564841884318"
    },
    {
      "date": "2026-04-28",
      "ticker": "TSLA",
      "volatility": "0.464471253466285",
      "expiry": "2027-03-19",
      "dte": 325,
      "implied_move": "111.5108814857908",
      "implied_move_perc": "0.296327102264305"
    },
    {
      "date": "2026-04-28",
      "ticker": "TSLA",
      "volatility": "0.475027222120773",
      "expiry": "2027-06-17",
      "dte": 415,
      "implied_move": "128.5025431539056",
      "implied_move_perc": "0.3414804523022517"
    },
    {
      "date": "2026-04-28",
      "ticker": "TSLA",
      "volatility": "0.485548664334041",
      "expiry": "2027-12-17",
      "dte": 598,
      "implied_move": "156.7618056084985",
      "implied_move_perc": "0.4165761312505258"
    },
    {
      "date": "2026-04-28",
      "ticker": "TSLA",
      "volatility": "0.485453485556699",
      "expiry": "2028-01-21",
      "dte": 633,
      "implied_move": "161.0878846234963",
      "implied_move_perc": "0.4280721793634992"
    },
    {
      "date": "2026-04-28",
      "ticker": "TSLA",
      "volatility": "0.487181837623458",
      "expiry": "2028-06-16",
      "dte": 780,
      "implied_move": "178.6464059696025",
      "implied_move_perc": "0.474731892579026"
    },
    {
      "date": "2026-04-28",
      "ticker": "TSLA",
      "volatility": "0.483959623277428",
      "expiry": "2028-12-15",
      "dte": 962,
      "implied_move": "196.0755698810651",
      "implied_move_perc": "0.521047853568281"
    }
  ]
}