{
  "_generated_at": "2026-07-20 10:22",
  "wsb": {
    "total_posts": 24,
    "sentiment_summary": "\ud83d\udd34 **BEARISH** \u2014 WSB sentiment heavily negative\n  Bullish posts: 0 (0 upvotes)\n  Bearish posts: 1 (4208 upvotes)\n  Top tickers: N/A",
    "top_tickers": [],
    "trending_tickers": {},
    "hot_posts": [
      {
        "title": "Welp that\u2019s my life screwed up forever",
        "ups": 8107,
        "url": "https://reddit.com/r/wallstreetbets/comments/1uzgyew/welp_thats_my_life_screwed_up_forever/",
        "tickers": []
      },
      {
        "title": "What Are Your Moves Tomorrow, July 20, 2026",
        "ups": 231,
        "url": "https://reddit.com/r/wallstreetbets/comments/1v10ane/what_are_your_moves_tomorrow_july_20_2026/",
        "tickers": []
      },
      {
        "title": "Every Release of Shrek Happens Right Before a Market Top",
        "ups": 4415,
        "url": "https://reddit.com/r/wallstreetbets/comments/1uzk1r3/every_release_of_shrek_happens_right_before_a/",
        "tickers": []
      },
      {
        "title": "321k SPACEX PUTS GAINS REALIZED.",
        "ups": 4208,
        "url": "https://reddit.com/r/wallstreetbets/comments/1uzrx6o/321k_spacex_puts_gains_realized/",
        "tickers": []
      },
      {
        "title": "INFINITE MONEY GLITCH",
        "ups": 3367,
        "url": "https://reddit.com/r/wallstreetbets/comments/1v0kgc0/infinite_money_glitch/",
        "tickers": []
      },
      {
        "title": "Technical analysis of where we're are and where we're heading: keep buying AI stocks",
        "ups": 2560,
        "url": "https://reddit.com/r/wallstreetbets/comments/1v0d3ky/technical_analysis_of_where_were_are_and_where/",
        "tickers": []
      },
      {
        "title": "'Give me my money back': South Korean traders' leveraged SK Hynix, Samsung bets unravel after selloff",
        "ups": 1741,
        "url": "https://reddit.com/r/wallstreetbets/comments/1v1benn/give_me_my_money_back_south_korean_traders/",
        "tickers": []
      }
    ]
  },
  "stocks": {
    "total_posts": 24,
    "sentiment_summary": "\ud83d\udfe2 **CONSTRUCTIVE** \u2014 Community focused on opportunities and analysis\n  Constructive posts: 2\n  Critical posts: 0\n  Educational posts: 0\n  Post types: \ud83d\udccb General(21), \ud83d\udcc8 Earnings Focus(2), \ud83d\udcb0 Dividend/Income(1)\n  Top tickers: MU",
    "top_tickers": [
      {
        "ticker": "MU",
        "count": 1
      }
    ],
    "sector_focus": [
      [
        "Technology",
        2
      ],
      [
        "Energy",
        1
      ]
    ],
    "key_themes": [
      "earnings",
      "buyback",
      "ipo",
      "cloud",
      "energy",
      "ai",
      "value",
      "growth"
    ],
    "hot_posts": [
      {
        "title": "GameStop Just Exercised $3.97B in eBay Calls, Acquiring ~39M Shares in Cash (13D Filing)",
        "ups": 1524,
        "url": "https://reddit.com/r/stocks/comments/1uzszgq/gamestop_just_exercised_397b_in_ebay_calls/",
        "tickers": [],
        "type": "\ud83d\udccb General"
      },
      {
        "title": "Apple surpassed Nvidia in market value, reclaiming its spot as the world\u2019s most valuable company",
        "ups": 645,
        "url": "https://reddit.com/r/stocks/comments/1uzhtu1/apple_surpassed_nvidia_in_market_value_reclaiming/",
        "tickers": [],
        "type": "\ud83d\udccb General"
      },
      {
        "title": "Netflix beat earnings, did its biggest buyback and then restricted access to its engagement data and fell 12% through two days.",
        "ups": 530,
        "url": "https://reddit.com/r/stocks/comments/1uzwpa8/netflix_beat_earnings_did_its_biggest_buyback_and/",
        "tickers": [],
        "type": "\ud83d\udcc8 Earnings Focus"
      },
      {
        "title": "Why MU is a huge buy",
        "ups": 329,
        "url": "https://reddit.com/r/stocks/comments/1uz4blv/why_mu_is_a_huge_buy/",
        "tickers": [
          "MU"
        ],
        "type": "\ud83d\udccb General"
      },
      {
        "title": "Is the stock market underestimating the conflict in the Middle East? Last night's attacks on energy and water plants are highly concerning",
        "ups": 328,
        "url": "https://reddit.com/r/stocks/comments/1uzxkob/is_the_stock_market_underestimating_the_conflict/",
        "tickers": [],
        "type": "\ud83d\udccb General"
      },
      {
        "title": "Will semis and memory recover?",
        "ups": 127,
        "url": "https://reddit.com/r/stocks/comments/1uzfttz/will_semis_and_memory_recover/",
        "tickers": [],
        "type": "\ud83d\udccb General"
      },
      {
        "title": "Trying to ACTUALLY understand what is happening with memory stocks; not asking for predictions",
        "ups": 254,
        "url": "https://reddit.com/r/stocks/comments/1uzong8/trying_to_actually_understand_what_is_happening/",
        "tickers": [],
        "type": "\ud83d\udccb General"
      }
    ]
  }
}