{
 "ticker": "CVS",
 "name": "CVS Health Corporation",
 "generated_at": "2026-07-21T11:45:01.745255+00:00",
 "price": 107.76,
 "change_pct": 0.27,
 "sector": "Healthcare",
 "signals": [
  "extended_rsi",
  "above_ma",
  "premium_pe"
 ],
 "technical": {
  "rsi_14": 65.2,
  "sma_20": 104.39,
  "sma_50": 98.74
 },
 "fundamentals": {
  "pe_ratio": 47.26535,
  "market_cap": "137.5B",
  "beta": 0.598,
  "dividend_yield": 0.0248
 },
 "council_analysis": {
  "score": 4
 },
 "upcoming_earnings": [],
 "recent_sec_filings": [],
 "reddit_mentions": []
}