{
 "ticker": "OMF",
 "name": "OneMain Holdings, Inc.",
 "generated_at": "2026-07-15T11:45:01.157484+00:00",
 "price": 60.1,
 "change_pct": 1.43,
 "sector": "Financial Services",
 "signals": [
  "above_ma",
  "value_pe"
 ],
 "technical": {
  "rsi_14": 57.5,
  "sma_20": 59.2,
  "sma_50": 56.3
 },
 "fundamentals": {
  "pe_ratio": 8.95678,
  "market_cap": "6.9B",
  "beta": 1.184,
  "dividend_yield": 0.0709
 },
 "council_analysis": {
  "score": 7
 },
 "upcoming_earnings": [],
 "recent_sec_filings": [],
 "reddit_mentions": []
}