{
 "ticker": "RL",
 "name": "Ralph Lauren Corporation",
 "generated_at": "2026-07-10T11:45:01.664242+00:00",
 "price": 385.76,
 "change_pct": 1.42,
 "sector": "Consumer Cyclical",
 "signals": [
  "rsi_dip"
 ],
 "technical": {
  "rsi_14": 38.2,
  "sma_20": 400.26,
  "sma_50": 374.1
 },
 "fundamentals": {
  "pe_ratio": 25.54702,
  "market_cap": "23.0B",
  "beta": 1.352,
  "dividend_yield": 0.0098
 },
 "council_analysis": {
  "score": 6
 },
 "upcoming_earnings": [],
 "recent_sec_filings": [],
 "reddit_mentions": []
}