{
  "generated_at": "2026-07-03 07:22:11",
  "date": "2026-07-03",
  "market_overview": {
    "source": "Seeking Alpha + BNN Bloomberg",
    "top_headlines": [
      {
        "title": "Meta Platforms eyes $6.5B MTIA AI chip deal with Samsung Foundry, Sedaily reports",
        "url": "https://seekingalpha.com/news/4609827-meta-platforms-eyes-65b-worth-mtia-ai-chip-deal-with-samsung-foundry?utm_source=feed_news_all&utm_medium=referral&feed_item_type=news",
        "source": "Seeking Alpha",
        "sentiment": "neutral",
        "summary": ""
      },
      {
        "title": "Texas man charged with manslaughter after Tesla crashes into home",
        "url": "https://seekingalpha.com/news/4609823-texas-man-charged-with-manslaughter-after-tesla-crashes-into-home?utm_source=feed_news_all&utm_medium=referral&feed_item_type=news",
        "source": "Seeking Alpha",
        "sentiment": "bearish",
        "summary": ""
      },
      {
        "title": "UK June composite PMI misses expectations, remains in contraction at 49.3",
        "url": "https://seekingalpha.com/news/4609819-uk-june-composite-pmi-misses-expectations-remains-in-contraction-at-493?utm_source=feed_news_all&utm_medium=referral&feed_item_type=news",
        "source": "Seeking Alpha",
        "sentiment": "neutral",
        "summary": ""
      },
      {
        "title": "Why the U.S. housing shortage might be nearing its end",
        "url": "https://seekingalpha.com/news/4608377-why-the-us-housing-shortage-might-be-nearing-its-end?utm_source=feed_news_all&utm_medium=referral&feed_item_type=news",
        "source": "Seeking Alpha",
        "sentiment": "neutral",
        "summary": ""
      },
      {
        "title": "Spotify said to remove 500K streams of song after suspicious Kalshi bets",
        "url": "https://seekingalpha.com/news/4609825-spotify-artificial-streams-kalshi-bets?utm_source=feed_news_all&utm_medium=referral&feed_item_type=news",
        "source": "Seeking Alpha",
        "sentiment": "neutral",
        "summary": ""
      },
      {
        "title": "Is the stock market closed on Friday? Trading details for July 3rd",
        "url": "https://seekingalpha.com/news/4609826-is-the-stock-market-closed-on-friday-trading-details-for-july-3rd?utm_source=feed_news_all&utm_medium=referral&feed_item_type=news",
        "source": "Seeking Alpha",
        "sentiment": "neutral",
        "summary": ""
      },
      {
        "title": "European markets mostly higher following Asian peers",
        "url": "https://seekingalpha.com/news/4609824-european-markets-mostly-higher-following-asian-peers?utm_source=feed_news_all&utm_medium=referral&feed_item_type=news",
        "source": "Seeking Alpha",
        "sentiment": "neutral",
        "summary": ""
      },
      {
        "title": "Micron: Not A Bubble, But Peak Cyclical Margins Suggest Caution",
        "url": "https://seekingalpha.com/article/4919648-micron-stock-q3-not-bubble-but-peak-cyclical-margins-suggest-caution?source=feed",
        "source": "Seeking Alpha",
        "sentiment": "neutral",
        "summary": ""
      },
      {
        "title": "The AI Bet Driving SpaceX",
        "url": "https://seekingalpha.com/article/4919647-ai-bet-driving-spacex?source=feed",
        "source": "Seeking Alpha",
        "sentiment": "neutral",
        "summary": ""
      },
      {
        "title": "Broadcom: Wall Street's ~$115 Billion FCF Consensus Crumbles Under Stresstesting",
        "url": "https://seekingalpha.com/article/4919640-broadcom-stock-wall-streets-115-billion-fcf-consensus-crumbles-under-stresstesting?source=feed",
        "source": "Seeking Alpha",
        "sentiment": "neutral",
        "summary": ""
      }
    ],
    "hot_tickers": [
      [
        "C",
        {
          "news_count": 15,
          "articles": [
            "Meta Platforms eyes $6.5B MTIA AI chip deal with Samsung Foundry, Sedaily reports",
            "Why the U.S. housing shortage might be nearing its end",
            "Is the stock market closed on Friday? Trading details for July 3rd",
            "Micron: Not A Bubble, But Peak Cyclical Margins Suggest Caution",
            "The AI Bet Driving SpaceX",
            "Broadcom: Wall Street's ~$115 Billion FCF Consensus Crumbles Under Stresstesting",
            "Commodities: Oil Under Pressure Amid Rebound In Middle East Flows",
            "Micron, Like Nvidia, Is Losing Its Premium",
            "2 Core Holdings To Anchor Decades Of Rising Income",
            "Top 10 Quant Stocks Of 2026 Up Nearly 70%",
            "Micron Is Now Everyone Else's Problem (Rating Downgrade)",
            "Two 7%+ Yielding Retirement Picks That I'd Buy For Income Growth",
            "The Unheard-Of A+ Stock: Why This Tech Pullback Is A Golden Opportunity",
            "Palantir: Don't Be The Last One Out",
            "CVC Plans \u20ac1.2 Billion of High-Yield Bonds to Fund Irca Buyout"
          ],
          "sentiments": [
            "neutral",
            "neutral",
            "neutral",
            "neutral",
            "neutral",
            "neutral",
            "neutral",
            "neutral",
            "neutral",
            "neutral",
            "bearish",
            "bullish",
            "neutral",
            "neutral",
            "bullish"
          ]
        }
      ],
      [
        "V",
        {
          "news_count": 15,
          "articles": [
            "Why the U.S. housing shortage might be nearing its end",
            "Is the stock market closed on Friday? Trading details for July 3rd",
            "Broadcom: Wall Street's ~$115 Billion FCF Consensus Crumbles Under Stresstesting",
            "Trump Just Went All-In On AI: Should You?",
            "Micron, Like Nvidia, Is Losing Its Premium",
            "Sandisk: Continued Memory Boom On Data Center Buildout",
            "Top 10 Quant Stocks Of 2026 Up Nearly 70%",
            "AI Bubble Burst: Meta Admits 'Excess Compute Capacity'",
            "Micron Is Now Everyone Else's Problem (Rating Downgrade)",
            "Two 7%+ Yielding Retirement Picks That I'd Buy For Income Growth",
            "Halftime Show: Expect A Historic 2nd Half Of 2026. Plus The Latest On My Personal Portfolio",
            "Building A $100,000 Dividend Portfolio With SCHD And July's Top High-Yield Picks",
            "The Unheard-Of A+ Stock: Why This Tech Pullback Is A Golden Opportunity",
            "Grantham Warns Of Biggest Bubble In History, Again",
            "CVC Plans \u20ac1.2 Billion of High-Yield Bonds to Fund Irca Buyout"
          ],
          "sentiments": [
            "neutral",
            "neutral",
            "neutral",
            "neutral",
            "neutral",
            "bullish",
            "neutral",
            "neutral",
            "bearish",
            "bullish",
            "neutral",
            "neutral",
            "neutral",
            "bullish",
            "bullish"
          ]
        }
      ],
      [
        "F",
        {
          "news_count": 10,
          "articles": [
            "UK June composite PMI misses expectations, remains in contraction at 49.3",
            "Why the U.S. housing shortage might be nearing its end",
            "European markets mostly higher following Asian peers",
            "Micron: Not A Bubble, But Peak Cyclical Margins Suggest Caution",
            "Commodities: Oil Under Pressure Amid Rebound In Middle East Flows",
            "Micron, Like Nvidia, Is Losing Its Premium",
            "2 Core Holdings To Anchor Decades Of Rising Income",
            "Two 7%+ Yielding Retirement Picks That I'd Buy For Income Growth",
            "Palantir: Don't Be The Last One Out",
            "China\u2019s State Iron Ore Buyer Extends Restrictions on Fortescue"
          ],
          "sentiments": [
            "neutral",
            "neutral",
            "neutral",
            "neutral",
            "neutral",
            "neutral",
            "neutral",
            "bullish",
            "neutral",
            "bullish"
          ]
        }
      ],
      [
        "SPY",
        {
          "news_count": 7,
          "articles": [
            "Is the stock market closed on Friday? Trading details for July 3rd",
            "Labor Market Tightens Despite Tepid Job Growth As Labor Force Declines Further Amid Crackdown On Illegal Immigration",
            "Trump Just Went All-In On AI: Should You?",
            "Most Of The S&P 500's 2026 Earnings Growth Is An Illusion",
            "Two 7%+ Yielding Retirement Picks That I'd Buy For Income Growth",
            "Halftime Show: Expect A Historic 2nd Half Of 2026. Plus The Latest On My Personal Portfolio",
            "Grantham Warns Of Biggest Bubble In History, Again"
          ],
          "sentiments": [
            "neutral",
            "neutral",
            "neutral",
            "bullish",
            "bullish",
            "neutral",
            "bullish"
          ]
        }
      ],
      [
        "QQQ",
        {
          "news_count": 7,
          "articles": [
            "Is the stock market closed on Friday? Trading details for July 3rd",
            "Labor Market Tightens Despite Tepid Job Growth As Labor Force Declines Further Amid Crackdown On Illegal Immigration",
            "Trump Just Went All-In On AI: Should You?",
            "Most Of The S&P 500's 2026 Earnings Growth Is An Illusion",
            "Two 7%+ Yielding Retirement Picks That I'd Buy For Income Growth",
            "Halftime Show: Expect A Historic 2nd Half Of 2026. Plus The Latest On My Personal Portfolio",
            "Grantham Warns Of Biggest Bubble In History, Again"
          ],
          "sentiments": [
            "neutral",
            "neutral",
            "neutral",
            "bullish",
            "bullish",
            "neutral",
            "bullish"
          ]
        }
      ]
    ],
    "sentiment_by_ticker": {
      "C": {
        "mentions": 15,
        "bullish": 2,
        "bearish": 1,
        "net_sentiment": 1
      },
      "V": {
        "mentions": 15,
        "bullish": 4,
        "bearish": 1,
        "net_sentiment": 3
      },
      "F": {
        "mentions": 10,
        "bullish": 2,
        "bearish": 0,
        "net_sentiment": 2
      },
      "SPY": {
        "mentions": 7,
        "bullish": 3,
        "bearish": 0,
        "net_sentiment": 3
      },
      "QQQ": {
        "mentions": 7,
        "bullish": 3,
        "bearish": 0,
        "net_sentiment": 3
      },
      "DIA": {
        "mentions": 6,
        "bullish": 2,
        "bearish": 0,
        "net_sentiment": 2
      },
      "MU": {
        "mentions": 5,
        "bullish": 0,
        "bearish": 1,
        "net_sentiment": -1
      },
      "AI": {
        "mentions": 4,
        "bullish": 0,
        "bearish": 0,
        "net_sentiment": 0
      },
      "MA": {
        "mentions": 3,
        "bullish": 0,
        "bearish": 0,
        "net_sentiment": 0
      },
      "BA": {
        "mentions": 3,
        "bullish": 0,
        "bearish": 0,
        "net_sentiment": 0
      }
    }
  },
  "options_flow": {
    "total_unusual_contracts": 25,
    "call_put_ratio": "7:18",
    "top_overbought_calls": [
      {
        "ticker": "TLT",
        "strike": 70.0,
        "expiration": "2026-07-06",
        "volume": 715,
        "vol_oi_ratio": 715.0,
        "premium": 1179750
      },
      {
        "ticker": "TLT",
        "strike": 84.0,
        "expiration": "2026-07-06",
        "volume": 152,
        "vol_oi_ratio": 152.0,
        "premium": 22800
      },
      {
        "ticker": "AAPL",
        "strike": 325.0,
        "expiration": "2026-07-06",
        "volume": 1336,
        "vol_oi_ratio": 133.6,
        "premium": 8016
      },
      {
        "ticker": "TSLA",
        "strike": 322.5,
        "expiration": "2026-07-06",
        "volume": 120,
        "vol_oi_ratio": 120.0,
        "premium": 827160
      },
      {
        "ticker": "AAPL",
        "strike": 340.0,
        "expiration": "2026-07-06",
        "volume": 116,
        "vol_oi_ratio": 116.0,
        "premium": 231
      }
    ],
    "top_overbought_puts": [
      {
        "ticker": "AAPL",
        "strike": 310.0,
        "expiration": "2026-07-06",
        "volume": 4349,
        "vol_oi_ratio": 4349.0,
        "premium": 1348190
      },
      {
        "ticker": "AAPL",
        "strike": 305.0,
        "expiration": "2026-07-06",
        "volume": 33057,
        "vol_oi_ratio": 3005.18,
        "premium": 3404871
      },
      {
        "ticker": "AAPL",
        "strike": 302.5,
        "expiration": "2026-07-06",
        "volume": 12543,
        "vol_oi_ratio": 1567.88,
        "premium": 840381
      },
      {
        "ticker": "NVDA",
        "strike": 215.0,
        "expiration": "2026-07-06",
        "volume": 1001,
        "vol_oi_ratio": 1001.0,
        "premium": 2152150
      },
      {
        "ticker": "WMT",
        "strike": 122.0,
        "expiration": "2026-07-10",
        "volume": 514,
        "vol_oi_ratio": 514.0,
        "premium": 750440
      }
    ]
  },
  "analysis_ideas": [
    {
      "type": "BULLISH_CONVERGENCE",
      "tickers": [
        "QQQ"
      ],
      "signal": "Positive news sentiment + heavy call buying",
      "action": "Consider bullish bias"
    },
    {
      "type": "MOST_UNUSUAL_FLOW",
      "tickers": [
        "AAPL"
      ],
      "signal": "Vol/OI ratio: 4349.0x \u2014 puts at $310.0 strike",
      "action": "Highest conviction put flow detected"
    },
    {
      "type": "SECTOR_SENTIMENT",
      "tickers": [
        "Other"
      ],
      "signal": "Highest positive sentiment sector",
      "action": "Look for long opportunities in Other"
    },
    {
      "type": "SECTOR_AVOID",
      "tickers": [
        "Tech"
      ],
      "signal": "Most negative sentiment sector",
      "action": "Avoid or hedge exposure in Tech"
    }
  ]
}