{
  "generated_at": "2026-06-18T12:00:33-04:00",
  "market_overview": {
    "total_net_gex": 2536433,
    "total_oi": 3327708,
    "current_price": 7493.58,
    "change_pct": 0.99
  },
  "tickers": {
    "SPX": {
      "current_price": 7493.58,
      "change_pct": 0.99,
      "gamma_regime": "bullish",
      "total_gex": 2536433,
      "total_dex": 79521157,
      "total_vex": 1048846369,
      "max_gex_strike": 750.0,
      "max_gex_value": 253005,
      "neutral_range": [],
      "gamma_profile": [
        {
          "strike": 700.0,
          "call_gex": 0,
          "put_gex": 92494,
          "net_gex": 92494,
          "dex": -3647536,
          "vex": 21532804,
          "oi": 267147
        },
        {
          "strike": 710.0,
          "call_gex": 0,
          "put_gex": 81309,
          "net_gex": 81309,
          "dex": -2927559,
          "vex": 15187350,
          "oi": 173208
        },
        {
          "strike": 715.0,
          "call_gex": 0,
          "put_gex": 52377,
          "net_gex": 52377,
          "dex": -1619215,
          "vex": 7560640,
          "oi": 96273
        },
        {
          "strike": 720.0,
          "call_gex": 0,
          "put_gex": 106681,
          "net_gex": 106681,
          "dex": -2890405,
          "vex": 12094546,
          "oi": 161284
        },
        {
          "strike": 725.0,
          "call_gex": 0,
          "put_gex": 84850,
          "net_gex": 84850,
          "dex": -2370643,
          "vex": 9470029,
          "oi": 112487
        },
        {
          "strike": 730.0,
          "call_gex": 60307,
          "put_gex": 120225,
          "net_gex": 180532,
          "dex": 2797924,
          "vex": 26898687,
          "oi": 235769
        },
        {
          "strike": 735.0,
          "call_gex": 44861,
          "put_gex": 183305,
          "net_gex": 228166,
          "dex": -1332671,
          "vex": 24963997,
          "oi": 233793
        },
        {
          "strike": 740.0,
          "call_gex": 61683,
          "put_gex": 191209,
          "net_gex": 252892,
          "dex": -1177435,
          "vex": 24203633,
          "oi": 207662
        },
        {
          "strike": 745.0,
          "call_gex": 110111,
          "put_gex": 116478,
          "net_gex": 226589,
          "dex": 2358129,
          "vex": 17962198,
          "oi": 154218
        },
        {
          "strike": 747.0,
          "call_gex": 0,
          "put_gex": 52609,
          "net_gex": 52609,
          "dex": -853976,
          "vex": 1173826,
          "oi": 17877
        },
        {
          "strike": 748.0,
          "call_gex": 45559,
          "put_gex": 0,
          "net_gex": 45559,
          "dex": 598137,
          "vex": 687857,
          "oi": 12538
        },
        {
          "strike": 750.0,
          "call_gex": 253005,
          "put_gex": 240763,
          "net_gex": 493768,
          "dex": 1037354,
          "vex": 44807637,
          "oi": 355170
        },
        {
          "strike": 751.0,
          "call_gex": 56150,
          "put_gex": 0,
          "net_gex": 56150,
          "dex": 714075,
          "vex": 1049215,
          "oi": 18690
        },
        {
          "strike": 752.0,
          "call_gex": 60336,
          "put_gex": 0,
          "net_gex": 60336,
          "dex": 817497,
          "vex": 1321709,
          "oi": 22745
        },
        {
          "strike": 753.0,
          "call_gex": 59289,
          "put_gex": 0,
          "net_gex": 59289,
          "dex": 783214,
          "vex": 1258155,
          "oi": 23592
        },
        {
          "strike": 755.0,
          "call_gex": 135766,
          "put_gex": 64601,
          "net_gex": 200367,
          "dex": 1869341,
          "vex": 19023773,
          "oi": 158385
        },
        {
          "strike": 760.0,
          "call_gex": 120170,
          "put_gex": 56032,
          "net_gex": 176202,
          "dex": 1360401,
          "vex": 23949102,
          "oi": 186331
        },
        {
          "strike": 765.0,
          "call_gex": 61601,
          "put_gex": 0,
          "net_gex": 61601,
          "dex": 3080709,
          "vex": 11230066,
          "oi": 93072
        },
        {
          "strike": 770.0,
          "call_gex": 69030,
          "put_gex": 0,
          "net_gex": 69030,
          "dex": 2940047,
          "vex": 11095870,
          "oi": 105668
        },
        {
          "strike": 775.0,
          "call_gex": 48070,
          "put_gex": 0,
          "net_gex": 48070,
          "dex": 2449355,
          "vex": 10543468,
          "oi": 92705
        },
        {
          "strike": 780.0,
          "call_gex": 76543,
          "put_gex": 0,
          "net_gex": 76543,
          "dex": 4159809,
          "vex": 18457646,
          "oi": 154919
        },
        {
          "strike": 800.0,
          "call_gex": 112671,
          "put_gex": 0,
          "net_gex": 112671,
          "dex": 6758858,
          "vex": 37472135,
          "oi": 280314
        },
        {
          "strike": 825.0,
          "call_gex": 51589,
          "put_gex": 0,
          "net_gex": 51589,
          "dex": 2282978,
          "vex": 15314570,
          "oi": 163861
        }
      ],
      "floor_zone": {
        "strike": 750.0,
        "net_gex": 493768,
        "total_gex": 493768,
        "range_start": 745.0,
        "range_end": 755.0,
        "strength": "strong",
        "narrative": "Gamma floor at $750"
      },
      "ceiling_zone": null,
      "narrative": "Net GEX: $+2,536,433 \u2014 dealers are long gamma (range-bound)",
      "expiry_data": {
        "all": {
          "gamma_profile": [
            {
              "strike": 700.0,
              "call_gex": 0,
              "put_gex": 92494,
              "net_gex": 92494,
              "dex": -3647536,
              "vex": 21532804,
              "oi": 267147
            },
            {
              "strike": 710.0,
              "call_gex": 0,
              "put_gex": 81309,
              "net_gex": 81309,
              "dex": -2927559,
              "vex": 15187350,
              "oi": 173208
            },
            {
              "strike": 715.0,
              "call_gex": 0,
              "put_gex": 52377,
              "net_gex": 52377,
              "dex": -1619215,
              "vex": 7560640,
              "oi": 96273
            },
            {
              "strike": 720.0,
              "call_gex": 0,
              "put_gex": 106681,
              "net_gex": 106681,
              "dex": -2890405,
              "vex": 12094546,
              "oi": 161284
            },
            {
              "strike": 725.0,
              "call_gex": 0,
              "put_gex": 84850,
              "net_gex": 84850,
              "dex": -2370643,
              "vex": 9470029,
              "oi": 112487
            },
            {
              "strike": 730.0,
              "call_gex": 60307,
              "put_gex": 120225,
              "net_gex": 180532,
              "dex": 2797924,
              "vex": 26898687,
              "oi": 235769
            },
            {
              "strike": 735.0,
              "call_gex": 44861,
              "put_gex": 183305,
              "net_gex": 228166,
              "dex": -1332671,
              "vex": 24963997,
              "oi": 233793
            },
            {
              "strike": 740.0,
              "call_gex": 61683,
              "put_gex": 191209,
              "net_gex": 252892,
              "dex": -1177435,
              "vex": 24203633,
              "oi": 207662
            },
            {
              "strike": 745.0,
              "call_gex": 110111,
              "put_gex": 116478,
              "net_gex": 226589,
              "dex": 2358129,
              "vex": 17962198,
              "oi": 154218
            },
            {
              "strike": 747.0,
              "call_gex": 0,
              "put_gex": 52609,
              "net_gex": 52609,
              "dex": -853976,
              "vex": 1173826,
              "oi": 17877
            },
            {
              "strike": 748.0,
              "call_gex": 45559,
              "put_gex": 0,
              "net_gex": 45559,
              "dex": 598137,
              "vex": 687857,
              "oi": 12538
            },
            {
              "strike": 750.0,
              "call_gex": 253005,
              "put_gex": 240763,
              "net_gex": 493768,
              "dex": 1037354,
              "vex": 44807637,
              "oi": 355170
            },
            {
              "strike": 751.0,
              "call_gex": 56150,
              "put_gex": 0,
              "net_gex": 56150,
              "dex": 714075,
              "vex": 1049215,
              "oi": 18690
            },
            {
              "strike": 752.0,
              "call_gex": 60336,
              "put_gex": 0,
              "net_gex": 60336,
              "dex": 817497,
              "vex": 1321709,
              "oi": 22745
            },
            {
              "strike": 753.0,
              "call_gex": 59289,
              "put_gex": 0,
              "net_gex": 59289,
              "dex": 783214,
              "vex": 1258155,
              "oi": 23592
            },
            {
              "strike": 755.0,
              "call_gex": 135766,
              "put_gex": 64601,
              "net_gex": 200367,
              "dex": 1869341,
              "vex": 19023773,
              "oi": 158385
            },
            {
              "strike": 760.0,
              "call_gex": 120170,
              "put_gex": 56032,
              "net_gex": 176202,
              "dex": 1360401,
              "vex": 23949102,
              "oi": 186331
            },
            {
              "strike": 765.0,
              "call_gex": 61601,
              "put_gex": 0,
              "net_gex": 61601,
              "dex": 3080709,
              "vex": 11230066,
              "oi": 93072
            },
            {
              "strike": 770.0,
              "call_gex": 69030,
              "put_gex": 0,
              "net_gex": 69030,
              "dex": 2940047,
              "vex": 11095870,
              "oi": 105668
            },
            {
              "strike": 775.0,
              "call_gex": 48070,
              "put_gex": 0,
              "net_gex": 48070,
              "dex": 2449355,
              "vex": 10543468,
              "oi": 92705
            },
            {
              "strike": 780.0,
              "call_gex": 76543,
              "put_gex": 0,
              "net_gex": 76543,
              "dex": 4159809,
              "vex": 18457646,
              "oi": 154919
            },
            {
              "strike": 800.0,
              "call_gex": 112671,
              "put_gex": 0,
              "net_gex": 112671,
              "dex": 6758858,
              "vex": 37472135,
              "oi": 280314
            },
            {
              "strike": 825.0,
              "call_gex": 51589,
              "put_gex": 0,
              "net_gex": 51589,
              "dex": 2282978,
              "vex": 15314570,
              "oi": 163861
            }
          ],
          "total_gex": 5653318,
          "total_dex": 79521157,
          "total_vex": 1048846369,
          "expiry_count": 32
        },
        "weekly": {
          "gamma_profile": [
            {
              "strike": 730.0,
              "call_gex": 0,
              "put_gex": 17849,
              "net_gex": 17849,
              "dex": -161560,
              "vex": 258707,
              "oi": 14493
            },
            {
              "strike": 733.0,
              "call_gex": 0,
              "put_gex": 25148,
              "net_gex": 25148,
              "dex": -258347,
              "vex": 381666,
              "oi": 15428
            },
            {
              "strike": 735.0,
              "call_gex": 0,
              "put_gex": 18566,
              "net_gex": 18566,
              "dex": -167389,
              "vex": 229727,
              "oi": 10082
            },
            {
              "strike": 740.0,
              "call_gex": 0,
              "put_gex": 43506,
              "net_gex": 43506,
              "dex": -384486,
              "vex": 425022,
              "oi": 15050
            },
            {
              "strike": 741.0,
              "call_gex": 0,
              "put_gex": 19089,
              "net_gex": 19089,
              "dex": -164297,
              "vex": 168969,
              "oi": 5930
            },
            {
              "strike": 742.0,
              "call_gex": 18055,
              "put_gex": 0,
              "net_gex": 18055,
              "dex": 360853,
              "vex": 159219,
              "oi": 5117
            },
            {
              "strike": 743.0,
              "call_gex": 21070,
              "put_gex": 21633,
              "net_gex": 42703,
              "dex": 129950,
              "vex": 354436,
              "oi": 11165
            },
            {
              "strike": 744.0,
              "call_gex": 21995,
              "put_gex": 0,
              "net_gex": 21995,
              "dex": 282900,
              "vex": 125698,
              "oi": 4284
            },
            {
              "strike": 745.0,
              "call_gex": 41200,
              "put_gex": 44523,
              "net_gex": 85723,
              "dex": 43800,
              "vex": 697955,
              "oi": 20320
            },
            {
              "strike": 746.0,
              "call_gex": 18570,
              "put_gex": 18560,
              "net_gex": 37130,
              "dex": 10997,
              "vex": 273921,
              "oi": 8046
            },
            {
              "strike": 747.0,
              "call_gex": 18987,
              "put_gex": 39856,
              "net_gex": 58843,
              "dex": -236312,
              "vex": 410039,
              "oi": 12372
            },
            {
              "strike": 748.0,
              "call_gex": 34463,
              "put_gex": 19407,
              "net_gex": 53870,
              "dex": 45842,
              "vex": 354680,
              "oi": 10723
            },
            {
              "strike": 749.0,
              "call_gex": 28920,
              "put_gex": 20624,
              "net_gex": 49544,
              "dex": -68496,
              "vex": 380311,
              "oi": 11165
            },
            {
              "strike": 750.0,
              "call_gex": 92353,
              "put_gex": 41209,
              "net_gex": 133562,
              "dex": 16392,
              "vex": 955962,
              "oi": 29879
            },
            {
              "strike": 751.0,
              "call_gex": 39764,
              "put_gex": 26213,
              "net_gex": 65977,
              "dex": -223910,
              "vex": 500191,
              "oi": 16199
            },
            {
              "strike": 752.0,
              "call_gex": 42766,
              "put_gex": 0,
              "net_gex": 42766,
              "dex": 263279,
              "vex": 286523,
              "oi": 10738
            },
            {
              "strike": 753.0,
              "call_gex": 39778,
              "put_gex": 0,
              "net_gex": 39778,
              "dex": 247069,
              "vex": 288166,
              "oi": 11275
            },
            {
              "strike": 754.0,
              "call_gex": 25488,
              "put_gex": 0,
              "net_gex": 25488,
              "dex": 147559,
              "vex": 184107,
              "oi": 8303
            },
            {
              "strike": 755.0,
              "call_gex": 46286,
              "put_gex": 19240,
              "net_gex": 65526,
              "dex": -260923,
              "vex": 528930,
              "oi": 24626
            },
            {
              "strike": 756.0,
              "call_gex": 17698,
              "put_gex": 0,
              "net_gex": 17698,
              "dex": 97601,
              "vex": 138746,
              "oi": 7983
            },
            {
              "strike": 760.0,
              "call_gex": 27425,
              "put_gex": 0,
              "net_gex": 27425,
              "dex": 137629,
              "vex": 242397,
              "oi": 26922
            }
          ],
          "total_gex": 1303801,
          "total_dex": 357942,
          "total_vex": 11856555,
          "expiry_count": 6
        },
        "monthly": {
          "gamma_profile": [
            {
              "strike": 600.0,
              "call_gex": 0,
              "put_gex": 26449,
              "net_gex": 26449,
              "dex": -1422657,
              "vex": 13349638,
              "oi": 371753
            },
            {
              "strike": 660.0,
              "call_gex": 0,
              "put_gex": 40080,
              "net_gex": 40080,
              "dex": -2696404,
              "vex": 23445535,
              "oi": 205087
            },
            {
              "strike": 665.0,
              "call_gex": 0,
              "put_gex": 29480,
              "net_gex": 29480,
              "dex": -1496297,
              "vex": 10618474,
              "oi": 132388
            },
            {
              "strike": 670.0,
              "call_gex": 0,
              "put_gex": 26962,
              "net_gex": 26962,
              "dex": -1429663,
              "vex": 10477935,
              "oi": 117400
            },
            {
              "strike": 690.0,
              "call_gex": 0,
              "put_gex": 28222,
              "net_gex": 28222,
              "dex": -1436556,
              "vex": 10654366,
              "oi": 94638
            },
            {
              "strike": 700.0,
              "call_gex": 0,
              "put_gex": 60270,
              "net_gex": 60270,
              "dex": -2866174,
              "vex": 17692586,
              "oi": 160500
            },
            {
              "strike": 710.0,
              "call_gex": 0,
              "put_gex": 50301,
              "net_gex": 50301,
              "dex": -2114717,
              "vex": 11308840,
              "oi": 105614
            },
            {
              "strike": 715.0,
              "call_gex": 0,
              "put_gex": 33893,
              "net_gex": 33893,
              "dex": -1289961,
              "vex": 6297276,
              "oi": 61221
            },
            {
              "strike": 720.0,
              "call_gex": 28155,
              "put_gex": 51146,
              "net_gex": 79301,
              "dex": 2106295,
              "vex": 16683211,
              "oi": 139050
            },
            {
              "strike": 725.0,
              "call_gex": 0,
              "put_gex": 39870,
              "net_gex": 39870,
              "dex": -1610149,
              "vex": 7226406,
              "oi": 60335
            },
            {
              "strike": 730.0,
              "call_gex": 45998,
              "put_gex": 60691,
              "net_gex": 106689,
              "dex": 2600138,
              "vex": 21405980,
              "oi": 161728
            },
            {
              "strike": 735.0,
              "call_gex": 30647,
              "put_gex": 94605,
              "net_gex": 125252,
              "dex": -463331,
              "vex": 19313960,
              "oi": 155259
            },
            {
              "strike": 740.0,
              "call_gex": 26670,
              "put_gex": 75069,
              "net_gex": 101739,
              "dex": -728105,
              "vex": 17980659,
              "oi": 124057
            },
            {
              "strike": 745.0,
              "call_gex": 49194,
              "put_gex": 28902,
              "net_gex": 78096,
              "dex": 2484466,
              "vex": 13437024,
              "oi": 94500
            },
            {
              "strike": 750.0,
              "call_gex": 77303,
              "put_gex": 130636,
              "net_gex": 207939,
              "dex": 625800,
              "vex": 35131378,
              "oi": 235579
            },
            {
              "strike": 755.0,
              "call_gex": 33080,
              "put_gex": 25761,
              "net_gex": 58841,
              "dex": 890175,
              "vex": 12352868,
              "oi": 74756
            },
            {
              "strike": 760.0,
              "call_gex": 44957,
              "put_gex": 41671,
              "net_gex": 86628,
              "dex": 635143,
              "vex": 18423051,
              "oi": 109611
            },
            {
              "strike": 765.0,
              "call_gex": 39274,
              "put_gex": 0,
              "net_gex": 39274,
              "dex": 2486002,
              "vex": 9099061,
              "oi": 56156
            },
            {
              "strike": 770.0,
              "call_gex": 46927,
              "put_gex": 0,
              "net_gex": 46927,
              "dex": 2310769,
              "vex": 8801418,
              "oi": 62104
            },
            {
              "strike": 775.0,
              "call_gex": 27606,
              "put_gex": 0,
              "net_gex": 27606,
              "dex": 1921569,
              "vex": 8458368,
              "oi": 48451
            },
            {
              "strike": 780.0,
              "call_gex": 50480,
              "put_gex": 0,
              "net_gex": 50480,
              "dex": 3061687,
              "vex": 13774583,
              "oi": 88065
            },
            {
              "strike": 800.0,
              "call_gex": 47003,
              "put_gex": 0,
              "net_gex": 47003,
              "dex": 3476436,
              "vex": 19942468,
              "oi": 116958
            }
          ],
          "total_gex": 2536372,
          "total_dex": 54485714,
          "total_vex": 799814737,
          "expiry_count": 13
        }
      }
    }
  }
}