{
  "generated_at": "2026-06-09T09:52:43-04:00",
  "market_overview": {
    "total_net_gex": 1982725,
    "total_oi": 2271195,
    "current_price": 7476.6,
    "change_pct": 0.96
  },
  "tickers": {
    "SPX": {
      "current_price": 7476.6,
      "change_pct": 0.96,
      "gamma_regime": "bullish",
      "total_gex": 1982725,
      "total_dex": 181931802,
      "total_vex": 39408761,
      "max_gex_strike": 750.0,
      "max_gex_value": 1237449,
      "neutral_range": [],
      "gamma_profile": [
        {
          "strike": 747.0,
          "call_gex": 777805,
          "put_gex": 0,
          "net_gex": 777805,
          "dex": 453159,
          "vex": 175886,
          "oi": 9857
        },
        {
          "strike": 748.0,
          "call_gex": 173608,
          "put_gex": 0,
          "net_gex": 173608,
          "dex": 247423,
          "vex": 118047,
          "oi": 11315
        },
        {
          "strike": 749.0,
          "call_gex": 105371,
          "put_gex": 0,
          "net_gex": 105371,
          "dex": 296771,
          "vex": 164275,
          "oi": 14124
        },
        {
          "strike": 750.0,
          "call_gex": 1237449,
          "put_gex": 0,
          "net_gex": 1237449,
          "dex": 11240079,
          "vex": 2882112,
          "oi": 185507
        },
        {
          "strike": 751.0,
          "call_gex": 92507,
          "put_gex": 0,
          "net_gex": 92507,
          "dex": 138075,
          "vex": 262538,
          "oi": 16545
        },
        {
          "strike": 752.0,
          "call_gex": 107352,
          "put_gex": 0,
          "net_gex": 107352,
          "dex": 186245,
          "vex": 386747,
          "oi": 15902
        },
        {
          "strike": 753.0,
          "call_gex": 44385,
          "put_gex": 0,
          "net_gex": 44385,
          "dex": 63611,
          "vex": 235802,
          "oi": 33239
        },
        {
          "strike": 754.0,
          "call_gex": 20034,
          "put_gex": 0,
          "net_gex": 20034,
          "dex": 21374,
          "vex": 101247,
          "oi": 21785
        },
        {
          "strike": 755.0,
          "call_gex": 488696,
          "put_gex": 0,
          "net_gex": 488696,
          "dex": 2786678,
          "vex": 3053263,
          "oi": 138456
        },
        {
          "strike": 756.0,
          "call_gex": 7112,
          "put_gex": 0,
          "net_gex": 7112,
          "dex": 11959,
          "vex": 57207,
          "oi": 18889
        },
        {
          "strike": 757.0,
          "call_gex": 3461,
          "put_gex": 0,
          "net_gex": 3461,
          "dex": 6525,
          "vex": 30202,
          "oi": 18288
        },
        {
          "strike": 758.0,
          "call_gex": 3308,
          "put_gex": 0,
          "net_gex": 3308,
          "dex": 9956,
          "vex": 29404,
          "oi": 22276
        },
        {
          "strike": 760.0,
          "call_gex": 181174,
          "put_gex": 0,
          "net_gex": 181174,
          "dex": 2693183,
          "vex": 2888891,
          "oi": 143132
        },
        {
          "strike": 763.0,
          "call_gex": 6387,
          "put_gex": 0,
          "net_gex": 6387,
          "dex": 28192,
          "vex": 130667,
          "oi": 41036
        },
        {
          "strike": 765.0,
          "call_gex": 100781,
          "put_gex": 0,
          "net_gex": 100781,
          "dex": 1411330,
          "vex": 2434048,
          "oi": 94734
        },
        {
          "strike": 770.0,
          "call_gex": 112591,
          "put_gex": 0,
          "net_gex": 112591,
          "dex": 732040,
          "vex": 2971524,
          "oi": 104221
        },
        {
          "strike": 775.0,
          "call_gex": 77406,
          "put_gex": 0,
          "net_gex": 77406,
          "dex": 688161,
          "vex": 2531557,
          "oi": 113393
        },
        {
          "strike": 780.0,
          "call_gex": 69749,
          "put_gex": 0,
          "net_gex": 69749,
          "dex": 785217,
          "vex": 2957955,
          "oi": 135718
        },
        {
          "strike": 785.0,
          "call_gex": 19538,
          "put_gex": 0,
          "net_gex": 19538,
          "dex": 348633,
          "vex": 1034136,
          "oi": 55744
        },
        {
          "strike": 790.0,
          "call_gex": 22921,
          "put_gex": 0,
          "net_gex": 22921,
          "dex": 411665,
          "vex": 1479598,
          "oi": 90653
        },
        {
          "strike": 795.0,
          "call_gex": 20591,
          "put_gex": 0,
          "net_gex": 20591,
          "dex": 303664,
          "vex": 1501224,
          "oi": 55650
        },
        {
          "strike": 800.0,
          "call_gex": 39754,
          "put_gex": 0,
          "net_gex": 39754,
          "dex": 1059598,
          "vex": 4235167,
          "oi": 287035
        },
        {
          "strike": 805.0,
          "call_gex": 5252,
          "put_gex": 0,
          "net_gex": 5252,
          "dex": 106698,
          "vex": 624729,
          "oi": 63251
        },
        {
          "strike": 810.0,
          "call_gex": 5012,
          "put_gex": 0,
          "net_gex": 5012,
          "dex": 178215,
          "vex": 654765,
          "oi": 59750
        },
        {
          "strike": 815.0,
          "call_gex": 5145,
          "put_gex": 0,
          "net_gex": 5145,
          "dex": 75284,
          "vex": 658710,
          "oi": 62108
        },
        {
          "strike": 820.0,
          "call_gex": 4207,
          "put_gex": 0,
          "net_gex": 4207,
          "dex": 86557,
          "vex": 674714,
          "oi": 80045
        },
        {
          "strike": 825.0,
          "call_gex": 5582,
          "put_gex": 0,
          "net_gex": 5582,
          "dex": 66193,
          "vex": 862220,
          "oi": 163076
        },
        {
          "strike": 830.0,
          "call_gex": 4880,
          "put_gex": 0,
          "net_gex": 4880,
          "dex": 91187,
          "vex": 869900,
          "oi": 57464
        },
        {
          "strike": 835.0,
          "call_gex": 5583,
          "put_gex": 0,
          "net_gex": 5583,
          "dex": 60401,
          "vex": 961005,
          "oi": 37549
        },
        {
          "strike": 850.0,
          "call_gex": 3797,
          "put_gex": 0,
          "net_gex": 3797,
          "dex": 32686,
          "vex": 686245,
          "oi": 120453
        }
      ],
      "floor_zone": {
        "strike": 750.0,
        "net_gex": 1237449,
        "total_gex": 1237449,
        "range_start": 745.0,
        "range_end": 755.0,
        "strength": "strong",
        "narrative": "Gamma floor at $750"
      },
      "ceiling_zone": null,
      "narrative": "Net GEX: $+1,982,725 \u2014 dealers are long gamma (range-bound)",
      "expiry_data": {
        "all": {
          "gamma_profile": [
            {
              "strike": 747.0,
              "call_gex": 777805,
              "put_gex": 0,
              "net_gex": 777805,
              "dex": 453159,
              "vex": 175886,
              "oi": 9857
            },
            {
              "strike": 748.0,
              "call_gex": 173608,
              "put_gex": 0,
              "net_gex": 173608,
              "dex": 247423,
              "vex": 118047,
              "oi": 11315
            },
            {
              "strike": 749.0,
              "call_gex": 105371,
              "put_gex": 0,
              "net_gex": 105371,
              "dex": 296771,
              "vex": 164275,
              "oi": 14124
            },
            {
              "strike": 750.0,
              "call_gex": 1237449,
              "put_gex": 0,
              "net_gex": 1237449,
              "dex": 11240079,
              "vex": 2882112,
              "oi": 185507
            },
            {
              "strike": 751.0,
              "call_gex": 92507,
              "put_gex": 0,
              "net_gex": 92507,
              "dex": 138075,
              "vex": 262538,
              "oi": 16545
            },
            {
              "strike": 752.0,
              "call_gex": 107352,
              "put_gex": 0,
              "net_gex": 107352,
              "dex": 186245,
              "vex": 386747,
              "oi": 15902
            },
            {
              "strike": 753.0,
              "call_gex": 44385,
              "put_gex": 0,
              "net_gex": 44385,
              "dex": 63611,
              "vex": 235802,
              "oi": 33239
            },
            {
              "strike": 754.0,
              "call_gex": 20034,
              "put_gex": 0,
              "net_gex": 20034,
              "dex": 21374,
              "vex": 101247,
              "oi": 21785
            },
            {
              "strike": 755.0,
              "call_gex": 488696,
              "put_gex": 0,
              "net_gex": 488696,
              "dex": 2786678,
              "vex": 3053263,
              "oi": 138456
            },
            {
              "strike": 756.0,
              "call_gex": 7112,
              "put_gex": 0,
              "net_gex": 7112,
              "dex": 11959,
              "vex": 57207,
              "oi": 18889
            },
            {
              "strike": 757.0,
              "call_gex": 3461,
              "put_gex": 0,
              "net_gex": 3461,
              "dex": 6525,
              "vex": 30202,
              "oi": 18288
            },
            {
              "strike": 758.0,
              "call_gex": 3308,
              "put_gex": 0,
              "net_gex": 3308,
              "dex": 9956,
              "vex": 29404,
              "oi": 22276
            },
            {
              "strike": 760.0,
              "call_gex": 181174,
              "put_gex": 0,
              "net_gex": 181174,
              "dex": 2693183,
              "vex": 2888891,
              "oi": 143132
            },
            {
              "strike": 763.0,
              "call_gex": 6387,
              "put_gex": 0,
              "net_gex": 6387,
              "dex": 28192,
              "vex": 130667,
              "oi": 41036
            },
            {
              "strike": 765.0,
              "call_gex": 100781,
              "put_gex": 0,
              "net_gex": 100781,
              "dex": 1411330,
              "vex": 2434048,
              "oi": 94734
            },
            {
              "strike": 770.0,
              "call_gex": 112591,
              "put_gex": 0,
              "net_gex": 112591,
              "dex": 732040,
              "vex": 2971524,
              "oi": 104221
            },
            {
              "strike": 775.0,
              "call_gex": 77406,
              "put_gex": 0,
              "net_gex": 77406,
              "dex": 688161,
              "vex": 2531557,
              "oi": 113393
            },
            {
              "strike": 780.0,
              "call_gex": 69749,
              "put_gex": 0,
              "net_gex": 69749,
              "dex": 785217,
              "vex": 2957955,
              "oi": 135718
            },
            {
              "strike": 785.0,
              "call_gex": 19538,
              "put_gex": 0,
              "net_gex": 19538,
              "dex": 348633,
              "vex": 1034136,
              "oi": 55744
            },
            {
              "strike": 790.0,
              "call_gex": 22921,
              "put_gex": 0,
              "net_gex": 22921,
              "dex": 411665,
              "vex": 1479598,
              "oi": 90653
            },
            {
              "strike": 795.0,
              "call_gex": 20591,
              "put_gex": 0,
              "net_gex": 20591,
              "dex": 303664,
              "vex": 1501224,
              "oi": 55650
            },
            {
              "strike": 800.0,
              "call_gex": 39754,
              "put_gex": 0,
              "net_gex": 39754,
              "dex": 1059598,
              "vex": 4235167,
              "oi": 287035
            },
            {
              "strike": 805.0,
              "call_gex": 5252,
              "put_gex": 0,
              "net_gex": 5252,
              "dex": 106698,
              "vex": 624729,
              "oi": 63251
            },
            {
              "strike": 810.0,
              "call_gex": 5012,
              "put_gex": 0,
              "net_gex": 5012,
              "dex": 178215,
              "vex": 654765,
              "oi": 59750
            },
            {
              "strike": 815.0,
              "call_gex": 5145,
              "put_gex": 0,
              "net_gex": 5145,
              "dex": 75284,
              "vex": 658710,
              "oi": 62108
            },
            {
              "strike": 820.0,
              "call_gex": 4207,
              "put_gex": 0,
              "net_gex": 4207,
              "dex": 86557,
              "vex": 674714,
              "oi": 80045
            },
            {
              "strike": 825.0,
              "call_gex": 5582,
              "put_gex": 0,
              "net_gex": 5582,
              "dex": 66193,
              "vex": 862220,
              "oi": 163076
            },
            {
              "strike": 830.0,
              "call_gex": 4880,
              "put_gex": 0,
              "net_gex": 4880,
              "dex": 91187,
              "vex": 869900,
              "oi": 57464
            },
            {
              "strike": 835.0,
              "call_gex": 5583,
              "put_gex": 0,
              "net_gex": 5583,
              "dex": 60401,
              "vex": 961005,
              "oi": 37549
            },
            {
              "strike": 850.0,
              "call_gex": 3797,
              "put_gex": 0,
              "net_gex": 3797,
              "dex": 32686,
              "vex": 686245,
              "oi": 120453
            }
          ],
          "total_gex": 3767996,
          "total_dex": 181931802,
          "total_vex": 39408761,
          "expiry_count": 35
        },
        "weekly": {
          "gamma_profile": [
            {
              "strike": 700.0,
              "call_gex": 0,
              "put_gex": 1,
              "net_gex": 1,
              "dex": -3,
              "vex": 13,
              "oi": 15937
            },
            {
              "strike": 724.0,
              "call_gex": 0,
              "put_gex": 2,
              "net_gex": 2,
              "dex": -2,
              "vex": 6,
              "oi": 2997
            },
            {
              "strike": 725.0,
              "call_gex": 0,
              "put_gex": 1,
              "net_gex": 1,
              "dex": -2,
              "vex": 6,
              "oi": 20751
            },
            {
              "strike": 730.0,
              "call_gex": 0,
              "put_gex": 3,
              "net_gex": 3,
              "dex": -2,
              "vex": 6,
              "oi": 39606
            },
            {
              "strike": 731.0,
              "call_gex": 0,
              "put_gex": 1,
              "net_gex": 1,
              "dex": -1,
              "vex": 2,
              "oi": 4233
            },
            {
              "strike": 733.0,
              "call_gex": 0,
              "put_gex": 2,
              "net_gex": 2,
              "dex": -1,
              "vex": 6,
              "oi": 19302
            },
            {
              "strike": 735.0,
              "call_gex": 0,
              "put_gex": 54,
              "net_gex": 54,
              "dex": -42,
              "vex": 174,
              "oi": 18848
            },
            {
              "strike": 736.0,
              "call_gex": 0,
              "put_gex": 12,
              "net_gex": 12,
              "dex": -8,
              "vex": 28,
              "oi": 7669
            },
            {
              "strike": 739.0,
              "call_gex": 0,
              "put_gex": 6,
              "net_gex": 6,
              "dex": -2,
              "vex": 7,
              "oi": 8386
            },
            {
              "strike": 740.0,
              "call_gex": 0,
              "put_gex": 4,
              "net_gex": 4,
              "dex": -1,
              "vex": 5,
              "oi": 27030
            },
            {
              "strike": 741.0,
              "call_gex": 0,
              "put_gex": 18,
              "net_gex": 18,
              "dex": -7,
              "vex": 28,
              "oi": 4608
            },
            {
              "strike": 743.0,
              "call_gex": 0,
              "put_gex": 32,
              "net_gex": 32,
              "dex": -7,
              "vex": 15,
              "oi": 4716
            },
            {
              "strike": 744.0,
              "call_gex": 0,
              "put_gex": 24,
              "net_gex": 24,
              "dex": -4,
              "vex": 16,
              "oi": 13843
            },
            {
              "strike": 745.0,
              "call_gex": 0,
              "put_gex": 13,
              "net_gex": 13,
              "dex": 0,
              "vex": 3,
              "oi": 35824
            },
            {
              "strike": 746.0,
              "call_gex": 0,
              "put_gex": 119,
              "net_gex": 119,
              "dex": -3,
              "vex": 7,
              "oi": 4095
            },
            {
              "strike": 747.0,
              "call_gex": 164859,
              "put_gex": 0,
              "net_gex": 164859,
              "dex": 23584,
              "vex": 30597,
              "oi": 3979
            },
            {
              "strike": 748.0,
              "call_gex": 1843,
              "put_gex": 0,
              "net_gex": 1843,
              "dex": 231,
              "vex": 673,
              "oi": 4765
            },
            {
              "strike": 749.0,
              "call_gex": 2170,
              "put_gex": 0,
              "net_gex": 2170,
              "dex": 574,
              "vex": 1726,
              "oi": 6232
            },
            {
              "strike": 750.0,
              "call_gex": 159,
              "put_gex": 0,
              "net_gex": 159,
              "dex": 31,
              "vex": 88,
              "oi": 22161
            },
            {
              "strike": 752.0,
              "call_gex": 255,
              "put_gex": 0,
              "net_gex": 255,
              "dex": 117,
              "vex": 415,
              "oi": 6531
            },
            {
              "strike": 753.0,
              "call_gex": 12,
              "put_gex": 0,
              "net_gex": 12,
              "dex": 4,
              "vex": 19,
              "oi": 24271
            },
            {
              "strike": 754.0,
              "call_gex": 16,
              "put_gex": 0,
              "net_gex": 16,
              "dex": 6,
              "vex": 15,
              "oi": 11394
            },
            {
              "strike": 755.0,
              "call_gex": 3,
              "put_gex": 0,
              "net_gex": 3,
              "dex": 1,
              "vex": 3,
              "oi": 35538
            },
            {
              "strike": 757.0,
              "call_gex": 8,
              "put_gex": 0,
              "net_gex": 8,
              "dex": 5,
              "vex": 18,
              "oi": 8964
            },
            {
              "strike": 758.0,
              "call_gex": 29,
              "put_gex": 0,
              "net_gex": 29,
              "dex": 23,
              "vex": 87,
              "oi": 10396
            },
            {
              "strike": 759.0,
              "call_gex": 6,
              "put_gex": 0,
              "net_gex": 6,
              "dex": 4,
              "vex": 19,
              "oi": 9483
            },
            {
              "strike": 760.0,
              "call_gex": 4,
              "put_gex": 0,
              "net_gex": 4,
              "dex": 3,
              "vex": 14,
              "oi": 50452
            },
            {
              "strike": 768.0,
              "call_gex": 2,
              "put_gex": 0,
              "net_gex": 2,
              "dex": 2,
              "vex": 8,
              "oi": 5191
            },
            {
              "strike": 770.0,
              "call_gex": 5,
              "put_gex": 0,
              "net_gex": 5,
              "dex": 7,
              "vex": 29,
              "oi": 11562
            },
            {
              "strike": 771.0,
              "call_gex": 3,
              "put_gex": 0,
              "net_gex": 3,
              "dex": 5,
              "vex": 21,
              "oi": 5947
            }
          ],
          "total_gex": 169671,
          "total_dex": 3446710,
          "total_vex": 34127,
          "expiry_count": 7
        },
        "monthly": {
          "gamma_profile": [
            {
              "strike": 749.0,
              "call_gex": 35590,
              "put_gex": 0,
              "net_gex": 35590,
              "dex": 100895,
              "vex": 78685,
              "oi": 1261
            },
            {
              "strike": 750.0,
              "call_gex": 958507,
              "put_gex": 0,
              "net_gex": 958507,
              "dex": 9346315,
              "vex": 2119150,
              "oi": 108451
            },
            {
              "strike": 751.0,
              "call_gex": 23806,
              "put_gex": 0,
              "net_gex": 23806,
              "dex": 48318,
              "vex": 61662,
              "oi": 1640
            },
            {
              "strike": 752.0,
              "call_gex": 43535,
              "put_gex": 0,
              "net_gex": 43535,
              "dex": 118706,
              "vex": 188360,
              "oi": 2364
            },
            {
              "strike": 753.0,
              "call_gex": 17519,
              "put_gex": 0,
              "net_gex": 17519,
              "dex": 21835,
              "vex": 76255,
              "oi": 2050
            },
            {
              "strike": 754.0,
              "call_gex": 11314,
              "put_gex": 0,
              "net_gex": 11314,
              "dex": 10279,
              "vex": 48837,
              "oi": 1401
            },
            {
              "strike": 755.0,
              "call_gex": 363245,
              "put_gex": 0,
              "net_gex": 363245,
              "dex": 2313271,
              "vex": 2250281,
              "oi": 39590
            },
            {
              "strike": 756.0,
              "call_gex": 2015,
              "put_gex": 0,
              "net_gex": 2015,
              "dex": 3008,
              "vex": 16792,
              "oi": 1944
            },
            {
              "strike": 757.0,
              "call_gex": 1060,
              "put_gex": 0,
              "net_gex": 1060,
              "dex": 1363,
              "vex": 8997,
              "oi": 2715
            },
            {
              "strike": 758.0,
              "call_gex": 1194,
              "put_gex": 0,
              "net_gex": 1194,
              "dex": 1337,
              "vex": 10253,
              "oi": 2337
            },
            {
              "strike": 760.0,
              "call_gex": 131153,
              "put_gex": 0,
              "net_gex": 131153,
              "dex": 2167328,
              "vex": 2111771,
              "oi": 52145
            },
            {
              "strike": 765.0,
              "call_gex": 87236,
              "put_gex": 0,
              "net_gex": 87236,
              "dex": 1048781,
              "vex": 2092358,
              "oi": 44820
            },
            {
              "strike": 770.0,
              "call_gex": 102550,
              "put_gex": 0,
              "net_gex": 102550,
              "dex": 618067,
              "vex": 2696847,
              "oi": 40983
            },
            {
              "strike": 775.0,
              "call_gex": 66162,
              "put_gex": 0,
              "net_gex": 66162,
              "dex": 558761,
              "vex": 2116882,
              "oi": 45216
            },
            {
              "strike": 780.0,
              "call_gex": 47383,
              "put_gex": 0,
              "net_gex": 47383,
              "dex": 623229,
              "vex": 1989189,
              "oi": 78636
            },
            {
              "strike": 785.0,
              "call_gex": 10938,
              "put_gex": 0,
              "net_gex": 10938,
              "dex": 306810,
              "vex": 645736,
              "oi": 34263
            },
            {
              "strike": 790.0,
              "call_gex": 20045,
              "put_gex": 0,
              "net_gex": 20045,
              "dex": 389596,
              "vex": 1248334,
              "oi": 48814
            },
            {
              "strike": 795.0,
              "call_gex": 16857,
              "put_gex": 0,
              "net_gex": 16857,
              "dex": 277117,
              "vex": 1177488,
              "oi": 34706
            },
            {
              "strike": 800.0,
              "call_gex": 23386,
              "put_gex": 0,
              "net_gex": 23386,
              "dex": 964639,
              "vex": 2855347,
              "oi": 101381
            },
            {
              "strike": 805.0,
              "call_gex": 4379,
              "put_gex": 0,
              "net_gex": 4379,
              "dex": 102213,
              "vex": 548050,
              "oi": 44975
            },
            {
              "strike": 810.0,
              "call_gex": 4682,
              "put_gex": 0,
              "net_gex": 4682,
              "dex": 176763,
              "vex": 626560,
              "oi": 32551
            },
            {
              "strike": 815.0,
              "call_gex": 4903,
              "put_gex": 0,
              "net_gex": 4903,
              "dex": 70379,
              "vex": 669599,
              "oi": 45656
            },
            {
              "strike": 820.0,
              "call_gex": 4145,
              "put_gex": 0,
              "net_gex": 4145,
              "dex": 86266,
              "vex": 669059,
              "oi": 57433
            },
            {
              "strike": 825.0,
              "call_gex": 5514,
              "put_gex": 0,
              "net_gex": 5514,
              "dex": 65902,
              "vex": 856159,
              "oi": 47735
            },
            {
              "strike": 830.0,
              "call_gex": 4858,
              "put_gex": 0,
              "net_gex": 4858,
              "dex": 91061,
              "vex": 867420,
              "oi": 35769
            },
            {
              "strike": 835.0,
              "call_gex": 5554,
              "put_gex": 0,
              "net_gex": 5554,
              "dex": 60237,
              "vex": 958387,
              "oi": 17155
            },
            {
              "strike": 840.0,
              "call_gex": 1168,
              "put_gex": 0,
              "net_gex": 1168,
              "dex": 13885,
              "vex": 207683,
              "oi": 21347
            },
            {
              "strike": 845.0,
              "call_gex": 1185,
              "put_gex": 0,
              "net_gex": 1185,
              "dex": 17594,
              "vex": 243536,
              "oi": 18840
            },
            {
              "strike": 850.0,
              "call_gex": 3651,
              "put_gex": 0,
              "net_gex": 3651,
              "dex": 31570,
              "vex": 662441,
              "oi": 69611
            },
            {
              "strike": 900.0,
              "call_gex": 1288,
              "put_gex": 0,
              "net_gex": 1288,
              "dex": 20880,
              "vex": 491756,
              "oi": 63435
            }
          ],
          "total_gex": 2010822,
          "total_dex": 96863095,
          "total_vex": 30436871,
          "expiry_count": 13
        }
      }
    }
  }
}