{
 "ticker": "AFRM",
 "name": "Affirm Holdings, Inc.",
 "generated_at": "2026-07-14T11:45:02.021652+00:00",
 "price": 82.46,
 "change_pct": -1.15,
 "sector": "Financial Services",
 "signals": [
  "extended_rsi",
  "above_ma",
  "premium_pe"
 ],
 "technical": {
  "rsi_14": 70.7,
  "sma_20": 78.38,
  "sma_50": 71.54
 },
 "fundamentals": {
  "pe_ratio": 74.96363,
  "market_cap": "27.6B",
  "beta": 3.674,
  "dividend_yield": null
 },
 "council_analysis": {
  "score": 4
 },
 "upcoming_earnings": [],
 "recent_sec_filings": [],
 "reddit_mentions": []
}