{
 "ticker": "HCA",
 "name": "HCA Healthcare, Inc.",
 "generated_at": "2026-07-15T11:45:01.157484+00:00",
 "price": 362.38,
 "change_pct": -7.26,
 "sector": "Healthcare",
 "signals": [
  "rsi_dip",
  "below_ma",
  "value_pe"
 ],
 "technical": {
  "rsi_14": 38.1,
  "sma_20": 394.26,
  "sma_50": 397.05
 },
 "fundamentals": {
  "pe_ratio": 12.483121,
  "market_cap": "80.4B",
  "beta": 1.128,
  "dividend_yield": 0.0077
 },
 "council_analysis": {
  "score": 6
 },
 "upcoming_earnings": [],
 "recent_sec_filings": [],
 "reddit_mentions": []
}