{
 "ticker": "MU",
 "name": "Micron Technology, Inc.",
 "generated_at": "2026-07-22T11:45:02.024909+00:00",
 "price": 933.86,
 "change_pct": 7.9,
 "sector": "Technology",
 "signals": [
  "oversold_rsi",
  "below_ma"
 ],
 "technical": {
  "rsi_14": 31.9,
  "sma_20": 996.05,
  "sma_50": 943.3
 },
 "fundamentals": {
  "pe_ratio": 21.113724,
  "market_cap": "1.05T",
  "beta": 2.142,
  "dividend_yield": 0.0006
 },
 "council_analysis": {
  "score": 6
 },
 "upcoming_earnings": [],
 "recent_sec_filings": [],
 "reddit_mentions": [
  {
   "sub": "wsb",
   "count": 1
  }
 ]
}