{
 "ticker": "PNC",
 "name": "PNC Financial Services Group, I",
 "generated_at": "2026-07-08T11:45:01.745733+00:00",
 "price": 255.81,
 "change_pct": 1.04,
 "sector": "Financial Services",
 "signals": [
  "overbought_rsi",
  "above_ma",
  "near_high",
  "value_pe"
 ],
 "technical": {
  "rsi_14": 84.7,
  "sma_20": 240.03,
  "sma_50": 227.28
 },
 "fundamentals": {
  "pe_ratio": 14.864033,
  "market_cap": "102.7B",
  "beta": 0.897,
  "dividend_yield": 0.0316
 },
 "council_analysis": {
  "score": 6
 },
 "upcoming_earnings": [],
 "recent_sec_filings": [],
 "reddit_mentions": []
}