{
 "ticker": "TJX",
 "name": "TJX Companies, Inc. (The)",
 "generated_at": "2026-07-16T11:45:01.566038+00:00",
 "price": 150.69,
 "change_pct": 0.11,
 "sector": "Consumer Cyclical",
 "signals": [
  "oversold_rsi",
  "below_ma"
 ],
 "technical": {
  "rsi_14": 26.4,
  "sma_20": 156.8,
  "sma_50": 156.33
 },
 "fundamentals": {
  "pe_ratio": 29.317122,
  "market_cap": "166.5B",
  "beta": 0.623,
  "dividend_yield": 0.0128
 },
 "council_analysis": {
  "score": 6
 },
 "upcoming_earnings": [],
 "recent_sec_filings": [],
 "reddit_mentions": []
}