{
 "ticker": "VMC",
 "name": "Vulcan Materials Company (Holdi",
 "generated_at": "2026-07-16T14:45:01.616912+00:00",
 "price": 292.25,
 "change_pct": 1.09,
 "sector": "Basic Materials",
 "signals": [
  "oversold_rsi",
  "premium_pe"
 ],
 "technical": {
  "rsi_14": 33.8,
  "sma_20": 298.56,
  "sma_50": 286.29
 },
 "fundamentals": {
  "pe_ratio": 34.626778,
  "market_cap": "37.9B",
  "beta": 1.05,
  "dividend_yield": 0.0072
 },
 "council_analysis": {
  "score": 6
 },
 "upcoming_earnings": [],
 "recent_sec_filings": [],
 "reddit_mentions": []
}